LICENSE
MANIFEST.in
README.md
setup.cfg
setup.py
carefree_portable.egg-info/PKG-INFO
carefree_portable.egg-info/SOURCES.txt
carefree_portable.egg-info/dependency_links.txt
carefree_portable.egg-info/entry_points.txt
carefree_portable.egg-info/requires.txt
carefree_portable.egg-info/top_level.txt
cfport/__init__.py
cfport/cli.py
cfport/config.py
cfport/console.py
cfport/constants.py
cfport/toolkit.py
cfport/executer/__init__.py
cfport/executer/schema.py
cfport/executer/blocks/__init__.py
cfport/executer/blocks/assets.py
cfport/executer/blocks/download.py
cfport/executer/blocks/hijack.py
cfport/executer/blocks/install.py
cfport/executer/blocks/launch.py
cfport/executer/blocks/prepare.py
cfport/executer/blocks/third_party/__init__.py
cfport/settings/defaults.json
cfport/settings/downloads/python_embeddables.json
cfport/settings/presets/carefree-portable.json
cfport/settings/presets/torch-2.1.0-cpu.json
cfport/settings/presets/torch-2.1.0-cu118.json