Metadata-Version: 2.1
Name: carefree-portable
Version: 0.1.1
Summary: Create portable (Python 🐍) projects on the fly 🚀 !
Author: carefree0910
Author-email: syameimaru.saki@gmail.com
Keywords: python portable
License-File: LICENSE
